riscv_pipelined/rtl/sources/imem.sv
module imem #(
  parameter DATA_WIDTH = 32,
  parameter MEM_DEPTH  = 1024,
  parameter MEM_FILE   = "program.hex"
)(
  input  logic                      clk, 
  input  logic                      rst,

  input  logic [DATA_WIDTH - 1 : 0] addr,
  input  logic                      instr_addr_valid,

  output reg   [DATA_WIDTH - 1 : 0] instr,
  output reg                        instr_valid
);

  integer i;
  // Instruction memory array
  logic [DATA_WIDTH - 1 : 0] mem [0 : MEM_DEPTH - 1];

  logic [DATA_WIDTH - 1 : 0] word_addr;

  // Program loading
  initial begin
    for (i = 0; i < MEM_DEPTH; i = i + 1) begin
      mem[i] = 32'h00000013;
    end

    $readmemh(MEM_FILE, mem);
  end

  assign word_addr = addr [DATA_WIDTH - 1 : 2];

  // Word-aligned instruction fetch
  // assign instr = mem[addr[31 : 2]];
  always @(posedge clk) begin
    if (rst) begin
      instr         <= '0;
      instr_valid   <= 1'b0;
    end else if (instr_addr_valid) begin
      if (word_addr < MEM_DEPTH) begin
        instr       <= mem[word_addr];
        instr_valid <= 1'b1;
      end else begin
        instr       <= 32'h00000013;
        instr_valid <= 1'b0;
      end
    end else begin
      instr         <= 32'h00000013;
      instr_valid   <= 1'b0;
    end
  end

endmodule

riscv_pipelined/rtl/sources/pc_reg.sv
module pc_reg #(
parameter DATA_WIDTH = 32
)(
  input  logic                      clk,
  input  logic                      rst,

  input  logic                      stall,

  input  logic [DATA_WIDTH - 1 : 0] next_pc,

  output logic [DATA_WIDTH - 1 : 0] pc
);

  always_ff @(posedge clk) begin
    if (rst) begin
      pc <= '0;
    end else if (!stall) begin
      pc <= next_pc;
    end

  end

endmodule

HaDes_Challenge/rtl/pc_mux.sv
module pc_mux #(
parameter DATA_WIDTH = 32
)(
  input  logic [DATA_WIDTH - 1 : 0] pc,

  input  logic                      redirect,
  input  logic [DATA_WIDTH - 1 : 0] redirect_pc,

  output logic [DATA_WIDTH - 1 : 0] next_pc
);

  always_comb begin
    if (redirect) begin
      next_pc = redirect_pc;
    end else begin
      next_pc = pc + 4;
    end

  end

endmodule

riscv_pipelined/rtl/sources/stage_if.sv
module stage_if #(
  parameter DATA_WIDTH = 32
)(
  input  logic                      clk,
  input  logic                      rst,

  // Hazard control
  input  logic                      stall,

  // Branch / jump redirect
  input  logic                      redirect,
  input  logic [DATA_WIDTH - 1 : 0] redirect_pc,

  // Instruction memory interface
  input  logic [DATA_WIDTH - 1 : 0] instr_in,
  input  logic                      instr_valid,

  output logic [DATA_WIDTH - 1 : 0] imem_addr,
  output logic                      instr_addr_valid,

  // IF/ID pipeline register outputs
  output logic [DATA_WIDTH - 1 : 0] if_id_pc,
  output logic [DATA_WIDTH - 1 : 0] if_id_instr,

  output logic                      if_id_valid
);

  // Internal PC signals
  logic [DATA_WIDTH - 1 : 0] pc;
  logic [DATA_WIDTH - 1 : 0] next_pc;

  logic                      fetch_stall;
  logic [DATA_WIDTH - 1 : 0] fetch_pc;

  logic                      pending_valid;
  logic [DATA_WIDTH - 1 : 0] pending_instr;
  logic [DATA_WIDTH - 1 : 0] pending_pc;

  // PC mux
  pc_mux pc_mux_01 (
    .pc          (pc),

    .redirect    (redirect),
    .redirect_pc (redirect_pc),

    .next_pc     (next_pc)
  );

  // PC register
  pc_reg pc_reg_01 (
    .clk         (clk),
    .rst         (rst),

    .stall       (fetch_stall),

    .next_pc     (next_pc),

    .pc          (pc)
  );

  // Instruction memory address
  assign imem_addr        = pc;

  assign fetch_stall      = stall || !instr_valid;

  assign instr_addr_valid = !stall;

  always_ff @(posedge clk) begin
    if (rst) begin
      fetch_pc <= '0;
    end else if (!stall && instr_addr_valid) begin
      fetch_pc <= pc;
    end
  end

  always_ff @(posedge clk) begin
    if (rst) begin
      pending_valid     <= 1'b0;
      if_id_pc          <= '0;
      if_id_instr       <= '0;
      if_id_valid       <= 1'b0;
    end else begin
      if (instr_valid && stall) begin
        pending_valid   <= 1'b1;
        pending_instr   <= instr_in;
        pending_pc      <= fetch_pc;
      end
      if (!stall) begin
        if (pending_valid) begin
          if_id_pc      <= pending_pc;
          if_id_instr   <= pending_instr;
          if_id_valid   <= 1'b1;
          pending_valid <= 1'b0;   
        end else if (instr_valid) begin
          if_id_pc      <= fetch_pc;
          if_id_instr   <= instr_in;
          if_id_valid   <= 1'b1;
        end else begin
          if_id_valid   <= 1'b0;
        end
      end else begin
        if_id_valid     <= 1'b0;
      end
    end
  end

  // // IF/ID pipeline register
  // always_ff @(posedge clk) begin : if_id_ff
  //   if (rst) begin
  //     if_id_pc    <= '0;
  //     if_id_instr <= '0;

  //     if_id_valid <= 1'b0;
  //   end else if (!fetch_stall && instr_valid) begin
  //     if_id_pc    <= fetch_pc;
  //     if_id_instr <= instr_in;

  //     if_id_valid <= 1'b1;
  //   end else begin
  //     if_id_valid <= 1'b0;
  //   end

  // end

endmodule

riscv_pipelined/rtl/sim/stage_if/tb_imem_stage_if.sv
// tb_imem_stage_if.sv
`timescale 1ns/1ps

module tb_imem_stage_if ();

  parameter DATA_WIDTH = 32;
  parameter MEM_DEPTH  = 1024;

  logic                      clk; 
  logic                      rst;

  logic                      stall; 

  logic                      redirect;
  logic [31 : 0]             redirect_pc;

  // DUT signals
  logic [31 : 0]             instr_in;
  logic                      instr_valid;

  logic [31 : 0]             imem_addr;
  logic                      instr_addr_valid;

  logic [31 : 0]             if_id_pc; 
  logic [31 : 0]             if_id_instr;

  logic                      if_id_valid;

  // DUT
  stage_if dut_stage_if (
    .clk              (clk),
    .rst              (rst),

    .stall            (stall),

    .redirect         (redirect),
    .redirect_pc      (redirect_pc),

    .instr_in         (instr_in),
    .instr_valid      (instr_valid),

    .imem_addr        (imem_addr),
    .instr_addr_valid (instr_addr_valid),

    .if_id_pc         (if_id_pc),
    .if_id_instr      (if_id_instr),

    .if_id_valid      (if_id_valid)
  );

  imem #(
    .DATA_WIDTH       (32),
    .MEM_DEPTH        (MEM_DEPTH),
    .MEM_FILE         ("../top_cpu/program.hex")
  ) dut_imem (
    .clk              (clk), 
    .rst              (rst),

    .addr             (imem_addr),
    .instr_addr_valid (instr_addr_valid),

    .instr            (instr_in),
    .instr_valid      (instr_valid)
  );

  // Clock
  initial begin
    clk = 0;
    forever #5 clk = ~clk;
  end

  // Dump waves
  initial begin
    $dumpfile ("tb_imem_stage_if.vcd");
    $dumpvars (0, tb_imem_stage_if);
  end

  // Debug monitor (optional)
  always @(posedge clk) begin
    #1;
    $display("--------------------------------");
    $display("TIME              = %0t", $time);
    $display("STALL             = %b", stall);
    $display("PC REQUEST        = %h", imem_addr);
    $display("ADDR VALID        = %b", instr_addr_valid);
    $display("IMEM INSTR        = %h", instr_in);
    $display("IMEM VALID        = %b", instr_valid);
    $display("IF_ID_PC          = %h", if_id_pc);
    $display("IF_ID_INSTR       = %h", if_id_instr);
    $display("IF_ID_VALID       = %b", if_id_valid);
  end

  // Self-check task
  task automatic check_if(
    input [31 : 0] exp_pc,
    input [31 : 0] exp_instr,
    input          exp_valid,
    input string   test_name
  );
    begin
      #1;
      if ((if_id_pc !== exp_pc) || (if_id_instr !== exp_instr) || (if_id_valid !== exp_valid)) begin
        $display("[FAIL] %s", test_name);
        $display("Expected PC    = %h", exp_pc);
        $display("Actual   PC    = %h", if_id_pc);
        $display("Expected INSTR = %h", exp_instr);
        $display("Actual   INSTR = %h", if_id_instr);
        $display("Expected VALID = %b", exp_valid);
        $display("Actual   VALID = %b", if_id_valid);
        $finish;
      end else begin
        $display("[PASS] %s", test_name);
      end
    end
  endtask

  // Test sequence
  initial begin
    rst         = 1'b1; 
    stall       = 1'b0; 
    redirect    = 1'b0; 
    redirect_pc = 0;

    repeat (2) @(posedge clk);
    rst         = 1'b0;
    @(posedge clk);   // pipeline start

    // Normal fetches
    @(posedge clk); @(posedge clk);
    check_if(32'd0, 32'h11111111, 1'b1, "FETCH PC=0");

    @(posedge clk);
    check_if(32'd4, 32'h22222222, 1'b1, "FETCH PC=4");

    @(posedge clk);
    check_if(32'd8, 32'h33333333, 1'b1, "FETCH PC=8");

    // Stall
    stall = 1'b1;
    @(posedge clk);
    check_if(32'd8, 32'h33333333, 1'b0, "STALL HOLD");

    stall = 1'b0;
    @(posedge clk);
    check_if(32'd12, 32'h44444444, 1'b1, "REFETCH AFTER STALL (0x0C)");

    @(posedge clk);
    check_if(32'd16, 32'hDEADBEEF, 1'b1, "FETCH AFTER STALL (0x10)");

    // Redirect test
    redirect = 1'b1; redirect_pc = 32'd64;
    @(posedge clk);
    redirect = 1'b0;

    @(posedge clk);
    @(posedge clk);
    check_if(32'd64, 32'hAAAAAAAA, 1'b1, "REDIRECT TARGET");

    @(posedge clk);
    check_if(32'd68, 32'h00a00093, 1'b1, "POST REDIRECT");

    $display("\nTESTS PASSED\n");
    $finish;
end

endmodule

riscv_pipelined/rtl/sim/stage_if/tb_imem_stage_if.vcd
$date
	Tue May 19 23:13:29 2026
$end
$version
	Icarus Verilog
$end
$timescale
	1ps
$end
$scope module tb_imem_stage_if $end
$var wire 1 ! instr_valid $end
$var wire 32 " instr_in [31:0] $end
$var wire 1 # instr_addr_valid $end
$var wire 32 $ imem_addr [31:0] $end
$var wire 1 % if_id_valid $end
$var wire 32 & if_id_pc [31:0] $end
$var wire 32 ' if_id_instr [31:0] $end
$var reg 1 ( clk $end
$var reg 1 ) redirect $end
$var reg 32 * redirect_pc [31:0] $end
$var reg 1 + rst $end
$var reg 1 , stall $end
$scope module dut_imem $end
$var wire 1 ( clk $end
$var wire 1 + rst $end
$var wire 32 - word_addr [31:0] $end
$var wire 1 # instr_addr_valid $end
$var wire 32 . addr [31:0] $end
$var reg 32 / instr [31:0] $end
$var reg 1 ! instr_valid $end
$var integer 32 0 i [31:0] $end
$upscope $end
$scope module dut_stage_if $end
$var wire 1 ( clk $end
$var wire 1 1 fetch_stall $end
$var wire 32 2 imem_addr [31:0] $end
$var wire 32 3 instr_in [31:0] $end
$var wire 1 ! instr_valid $end
$var wire 1 ) redirect $end
$var wire 32 4 redirect_pc [31:0] $end
$var wire 1 + rst $end
$var wire 1 , stall $end
$var wire 32 5 pc [31:0] $end
$var wire 32 6 next_pc [31:0] $end
$var wire 1 # instr_addr_valid $end
$var reg 32 7 fetch_pc [31:0] $end
$var reg 32 8 if_id_instr [31:0] $end
$var reg 32 9 if_id_pc [31:0] $end
$var reg 1 % if_id_valid $end
$var reg 32 : pending_instr [31:0] $end
$var reg 32 ; pending_pc [31:0] $end
$var reg 1 < pending_valid $end
$scope module pc_mux_01 $end
$var wire 1 ) redirect $end
$var wire 32 = redirect_pc [31:0] $end
$var wire 32 > pc [31:0] $end
$var reg 32 ? next_pc [31:0] $end
$upscope $end
$scope module pc_reg_01 $end
$var wire 1 ( clk $end
$var wire 32 @ next_pc [31:0] $end
$var wire 1 + rst $end
$var wire 1 1 stall $end
$var reg 32 A pc [31:0] $end
$upscope $end
$upscope $end
$scope task check_if $end
$upscope $end
$upscope $end
$enddefinitions $end
#0
$dumpvars
bx A
bx @
bx ?
bx >
b0 =
x<
bx ;
bx :
bx 9
bx 8
bx 7
bx 6
bx 5
b0 4
bx 3
bx 2
x1
b10000000000 0
bx /
bx .
b0xxxxxxxxxxxxxxxxxxxxxxxxxxxxxx -
0,
1+
b0 *
0)
0(
bx '
bx &
x%
bx $
1#
bx "
x!
$end
#5000
b0 -
b100 6
b100 ?
b100 @
11
b0 $
b0 .
b0 2
b0 5
b0 >
b0 A
b0 7
0%
b0 '
b0 8
b0 &
b0 9
0<
0!
b0 "
b0 /
b0 3
1(
#10000
0(
#15000
0+
1(
#20000
0(
#25000
01
1!
b10001000100010001000100010001 "
b10001000100010001000100010001 /
b10001000100010001000100010001 3
1(
#30000
0(
#35000
b1 -
b1000 6
b1000 ?
b1000 @
1%
b10001000100010001000100010001 '
b10001000100010001000100010001 8
b100 $
b100 .
b100 2
b100 5
b100 >
b100 A
1(
#40000
0(
#45000
b10 -
b1100 6
b1100 ?
b1100 @
b1000 $
b1000 .
b1000 2
b1000 5
b1000 >
b1000 A
b100 7
b100010001000100010001000100010 "
b100010001000100010001000100010 /
b100010001000100010001000100010 3
1(
#50000
0(
#55000
b11 -
b10000 6
b10000 ?
b10000 @
b110011001100110011001100110011 "
b110011001100110011001100110011 /
b110011001100110011001100110011 3
b100010001000100010001000100010 '
b100010001000100010001000100010 8
b100 &
b100 9
b1000 7
b1100 $
b1100 .
b1100 2
b1100 5
b1100 >
b1100 A
1(
#60000
0(
#65000
b100 -
b10100 6
b10100 ?
b10100 @
b10000 $
b10000 .
b10000 2
b10000 5
b10000 >
b10000 A
b1100 7
b110011001100110011001100110011 '
b110011001100110011001100110011 8
b1000 &
b1000 9
b1000100010001000100010001000100 "
b1000100010001000100010001000100 /
b1000100010001000100010001000100 3
1(
#66000
11
0#
1,
#70000
0(
#75000
0!
b10011 "
b10011 /
b10011 3
0%
b1100 ;
b1000100010001000100010001000100 :
1<
1(
#76000
1#
0,
#80000
0(
#85000
01
b10000 7
0<
1%
b1000100010001000100010001000100 '
b1000100010001000100010001000100 8
b1100 &
b1100 9
1!
b11011110101011011011111011101111 "
b11011110101011011011111011101111 /
b11011110101011011011111011101111 3
1(
#90000
0(
#95000
b101 -
b11000 6
b11000 ?
b11000 @
b11011110101011011011111011101111 '
b11011110101011011011111011101111 8
b10000 &
b10000 9
b10100 $
b10100 .
b10100 2
b10100 5
b10100 >
b10100 A
1(
#96000
b1000000 6
b1000000 ?
b1000000 @
b1000000 *
b1000000 4
b1000000 =
1)
#100000
0(
#105000
b10000 -
b1000000 $
b1000000 .
b1000000 2
b1000000 5
b1000000 >
b1000000 A
b10100 7
b1000100 6
b1000100 ?
b1000100 @
0)
1(
#110000
0(
#115000
b10001 -
b1001000 6
b1001000 ?
b1001000 @
b10101010101010101010101010101010 "
b10101010101010101010101010101010 /
b10101010101010101010101010101010 3
b10100 &
b10100 9
b1000000 7
b1000100 $
b1000100 .
b1000100 2
b1000100 5
b1000100 >
b1000100 A
1(
#120000
0(
#125000
b10010 -
b1001100 6
b1001100 ?
b1001100 @
b1001000 $
b1001000 .
b1001000 2
b1001000 5
b1001000 >
b1001000 A
b1000100 7
b10101010101010101010101010101010 '
b10101010101010101010101010101010 8
b1000000 &
b1000000 9
b101000000000000010010011 "
b101000000000000010010011 /
b101000000000000010010011 3
1(
#130000
0(
#135000
b10011 -
b1010000 6
b1010000 ?
b1010000 @
b1010000000000000100010011 "
b1010000000000000100010011 /
b1010000000000000100010011 3
b101000000000000010010011 '
b101000000000000010010011 8
b1000100 &
b1000100 9
b1001000 7
b1001100 $
b1001100 .
b1001100 2
b1001100 5
b1001100 >
b1001100 A
1(
