rtl/sources/alu.vhd
library ieee;
use ieee.std_logic_1164.all;
use ieee.numeric_std.all;

library work;
use work.memory_pkg.all;
use work.cpu_pkg.all;

entity alu is 

  port (

    op1    : in  std_logic_vector (WORD_SIZE - 1 downto 0);
    op2    : in  std_logic_vector (WORD_SIZE - 1 downto 0);
    aluop  : in  ALU_OP_TYPE_t;                             

    result : out std_logic_vector (WORD_SIZE - 1 downto 0)

  );

end entity;

architecture rtl of alu is begin

  -- Combinational process for the alu operations
  process (op1, op2, aluop) begin
    case aluop is
      
      -- Addition : Used for ADD, ADDI, loads/stores address calculation and PC + 4, when op1 = PC, op2 = 4
      when ALU_OP_TYPE_ADD  => result   <= std_logic_vector (unsigned (op1) + unsigned (op2));

      -- Pass : Simply passes the second operand. Used for LUI (op2 = immediate shifted left 12) and AUIPC (op2 = PC + immediate)
      when ALU_OP_TYPE_PASS => result   <= op2;

      -- Substraction  : Used for SUB
      when ALU_OP_TYPE_SUB  => result   <= std_logic_vector (unsigned (op1) - unsigned (op2));

      -- Bitwise AND : Used for AND, ANDI
      when ALU_OP_TYPE_AND  => result   <= op1 and op2;
   
      -- Bitwise OR : Used for OR, ORI
      when ALU_OP_TYPE_OR   => result   <= op1 or op2;

      -- Bitwise XOR : USed for XOR, XORI.
      when ALU_OP_TYPE_XOR  => result   <= op1 xor op2;

      -- Logical left shift: used for SLL, SLLI. Shift amount is taken from the lower 5 bits of op2 (RV32I).
      when ALU_OP_TYPE_SLL  => result   <= std_logic_vector(shift_left(unsigned(op1), to_integer(unsigned(op2(4 downto 0)))));

      -- Logical right shift: used for SRL, SRLI.
      when ALU_OP_TYPE_SRL  => result   <= std_logic_vector(shift_right(unsigned(op1), to_integer(unsigned(op2(4 downto 0)))));

      -- Arithmetic right shift: used for SRA, SRAI. Operand is treated as signed to preserve the sign bit.
      when ALU_OP_TYPE_SRA  => result   <= std_logic_vector(shift_right(signed(op1), to_integer(unsigned(op2(4 downto 0)))));

      -- Set less than (signed): used for SLT, SLTI. Result is 1 if op1 < op2 (signed), else 0.
      when ALU_OP_TYPE_SLT  => if signed(op1) < signed(op2) then
                                 result <= x"00000001";
                               else
                                 result <= x"00000000";
                               end if;

      -- Set less than (unsigned): used for SLTU, SLTIU. Result is 1 if op1 < op2 (unsigned), else 0.
      when ALU_OP_TYPE_SLTU => if unsigned(op1) < unsigned(op2) then
                                 result <= x"00000001";
                               else
                                 result <= x"00000000";
                               end if;

      -- Default case (should not occur if aluop is properly driven).
      when others =>             result <= (others => '0');

    end case;
  end process;

end architecture rtl;

rtl/sim/alu/tb_alu.vhd
library ieee;
use ieee.std_logic_1164.all;
use ieee.numeric_std.all;
use std.textio.all;
use ieee.std_logic_textio.all;

library work;
use work.cpu_pkg.all;
use work.memory_pkg.all;

entity tb_alu is
end entity;

architecture sim of tb_alu is

  function expected_result(
    a, b : std_logic_vector(31 downto 0);
    op   : ALU_OP_TYPE_t
  ) return std_logic_vector is
    variable shamt : natural range 0 to 31;
  begin
    shamt := to_integer(unsigned(b(4 downto 0)));
    case op is
      when ALU_OP_TYPE_ADD  => return std_logic_vector(unsigned(a) + unsigned(b));
      when ALU_OP_TYPE_PASS => return b;
      when ALU_OP_TYPE_SUB  => return std_logic_vector(unsigned(a) - unsigned(b));
      when ALU_OP_TYPE_AND  => return a and b;
      when ALU_OP_TYPE_OR   => return a or b;
      when ALU_OP_TYPE_XOR  => return a xor b;
      when ALU_OP_TYPE_SLL  => return std_logic_vector(shift_left(unsigned(a), shamt));
      when ALU_OP_TYPE_SRL  => return std_logic_vector(shift_right(unsigned(a), shamt));
      when ALU_OP_TYPE_SRA  => return std_logic_vector(shift_right(signed(a), shamt));
      when ALU_OP_TYPE_SLT  =>
        if signed(a) < signed(b) then
          return x"00000001";
        else
          return x"00000000";
        end if;
      when ALU_OP_TYPE_SLTU =>
        if unsigned(a) < unsigned(b) then
          return x"00000001";
        else
          return x"00000000";
        end if;
      when others => return x"00000000";   -- replaced (others => '0')
    end case;
  end function;

  -----------------------------------------------------------------------------
  -- 32-bit LFSR procedure
  -- Polynomial: x^32 + x^22 + x^2 + x + 1 (taps at bits 31,21,1,0)
  -- Updates seed and returns the new random value via rand.
  -----------------------------------------------------------------------------
  procedure lfsr_random(
    variable seed : inout std_logic_vector(31 downto 0);
    variable rand : out   std_logic_vector(31 downto 0)
  ) is
    variable feedback : std_logic;
    variable new_seed : std_logic_vector(31 downto 0);
  begin
    feedback := seed(31) xor seed(21) xor seed(1) xor seed(0);
    new_seed := seed(30 downto 0) & feedback;
    seed := new_seed;          -- update seed for next call
    rand := new_seed;          -- output the new value
  end procedure;

  -----------------------------------------------------------------------------
  -- DUT signals
  -----------------------------------------------------------------------------
  signal op1, op2, result : std_logic_vector(31 downto 0);
  signal aluop            : ALU_OP_TYPE_t;

  -----------------------------------------------------------------------------
  -- Test control (no shared variables - will be moved inside the process)
  -----------------------------------------------------------------------------
  constant NUM_RANDOM_TESTS : natural := 100;

begin

  -----------------------------------------------------------------------------
  -- Instantiate ALU
  -----------------------------------------------------------------------------
  uut: entity work.alu
    port map (
      op1    => op1,
      op2    => op2,
      aluop  => aluop,
      result => result
    );

  -----------------------------------------------------------------------------
  -- Main stimulus
  -----------------------------------------------------------------------------
  process
    -- Variables for test counts (now ordinary variables inside the process)
    variable error_cnt : natural := 0;
    variable test_cnt  : natural := 0;

    ---------------------------------------------------------------------------
    -- Apply and check one vector
    ---------------------------------------------------------------------------
    procedure test_vector(
      a, b   : std_logic_vector(31 downto 0);
      op     : ALU_OP_TYPE_t;
      name   : string
    ) is
      variable exp : std_logic_vector(31 downto 0);
      variable l   : line;
    begin
      op1 <= a;
      op2 <= b;
      aluop <= op;
      wait for 10 ns;
      exp := expected_result(a, b, op);
      test_cnt := test_cnt + 1;
      if result /= exp then
        write(l, string'("Mismatch for " & name & ": "));
        write(l, string'("a=0x")); hwrite(l, a);
        write(l, string'(" b=0x")); hwrite(l, b);
        write(l, string'(" expected=0x")); hwrite(l, exp);
        write(l, string'(" got=0x")); hwrite(l, result);
        report l.all severity error;
        deallocate(l);
        error_cnt := error_cnt + 1;
      end if;
    end procedure;

    ---------------------------------------------------------------------------
    -- Test each operation
    ---------------------------------------------------------------------------
    procedure test_op(op : ALU_OP_TYPE_t; name : string) is
      type word_array is array (natural range <>) of std_logic_vector(31 downto 0);
      constant corner_a : word_array(0 to 5) := (
        x"00000000", x"FFFFFFFF", x"55555555",
        x"AAAAAAAA", x"80000000", x"7FFFFFFF"
      );
      constant corner_b : word_array(0 to 5) := (
        x"00000000", x"FFFFFFFF", x"55555555",
        x"AAAAAAAA", x"00000001", x"0000001F"
      );

      variable seed   : std_logic_vector(31 downto 0) := x"12345678";
      variable rand_a, rand_b : std_logic_vector(31 downto 0);
    begin
      report "Testing " & name & " ...";

      -- Corner cases
      for i in corner_a'range loop
        for j in corner_b'range loop
          test_vector(corner_a(i), corner_b(j), op, name);
        end loop;
      end loop;

      -- Random tests using LFSR procedure
      for k in 1 to NUM_RANDOM_TESTS loop
        lfsr_random(seed, rand_a);
        lfsr_random(seed, rand_b);
        test_vector(rand_a, rand_b, op, name);
      end loop;
    end procedure;

  begin
    test_op(ALU_OP_TYPE_ADD,  "ADD");
    test_op(ALU_OP_TYPE_PASS, "PASS");
    test_op(ALU_OP_TYPE_SUB,  "SUB");
    test_op(ALU_OP_TYPE_AND,  "AND");
    test_op(ALU_OP_TYPE_OR,   "OR");
    test_op(ALU_OP_TYPE_XOR,  "XOR");
    test_op(ALU_OP_TYPE_SLL,  "SLL");
    test_op(ALU_OP_TYPE_SRL,  "SRL");
    test_op(ALU_OP_TYPE_SRA,  "SRA");
    test_op(ALU_OP_TYPE_SLT,  "SLT");
    test_op(ALU_OP_TYPE_SLTU, "SLTU");

    -- Summary
    report "Total tests: " & integer'image(test_cnt);
    if error_cnt = 0 then
      report "SUCCESS: All tests passed." severity note;
    else
      report "FAILURE: " & integer'image(error_cnt) & " errors occurred." severity failure;
    end if;
    wait;
  end process;

end architecture;

rtl/sim/alu/alu_waveform.vcd
$date
  Fri Mar 13 22:50:35 2026
$end
$version
  GHDL v0
$end
$timescale
  1 fs
$end
$scope module standard $end
$upscope $end
$scope module textio $end
$upscope $end
$scope module std_logic_1164 $end
$upscope $end
$scope module numeric_std $end
$upscope $end
$scope module std_logic_textio $end
$upscope $end
$scope module cpu_pkg $end
$upscope $end
$scope module memory_pkg $end
$upscope $end
$scope module tb_alu $end
$var reg 32 ! op1[31:0] $end
$var reg 32 " op2[31:0] $end
$var reg 32 # result[31:0] $end
$comment aluop is not handled $end
$scope module uut $end
$var reg 32 $ op1[31:0] $end
$var reg 32 % op2[31:0] $end
$comment aluop is not handled $end
$var reg 32 & result[31:0] $end
$upscope $end
$upscope $end
$enddefinitions $end
#0
b00000000000000000000000000000000 !
b00000000000000000000000000000000 "
b00000000000000000000000000000000 #
b00000000000000000000000000000000 $
b00000000000000000000000000000000 %
b00000000000000000000000000000000 &
#10000000
b11111111111111111111111111111111 "
b11111111111111111111111111111111 #
b11111111111111111111111111111111 %
b11111111111111111111111111111111 &
#20000000
b01010101010101010101010101010101 "
b01010101010101010101010101010101 #
b01010101010101010101010101010101 %
b01010101010101010101010101010101 &
#30000000
b10101010101010101010101010101010 "
b10101010101010101010101010101010 #
b10101010101010101010101010101010 %
b10101010101010101010101010101010 &
#40000000
b00000000000000000000000000000001 "
b00000000000000000000000000000001 #
b00000000000000000000000000000001 %
b00000000000000000000000000000001 &
#50000000
b00000000000000000000000000011111 "
b00000000000000000000000000011111 #
b00000000000000000000000000011111 %
b00000000000000000000000000011111 &
#60000000
b11111111111111111111111111111111 !
b00000000000000000000000000000000 "
b11111111111111111111111111111111 #
b11111111111111111111111111111111 $
b00000000000000000000000000000000 %
b11111111111111111111111111111111 &
#70000000
b11111111111111111111111111111111 "
b11111111111111111111111111111110 #
b11111111111111111111111111111111 %
b11111111111111111111111111111110 &
#80000000
b01010101010101010101010101010101 "
b01010101010101010101010101010100 #
b01010101010101010101010101010101 %
b01010101010101010101010101010100 &
#90000000
b10101010101010101010101010101010 "
b10101010101010101010101010101001 #
b10101010101010101010101010101010 %
b10101010101010101010101010101001 &
#100000000
b00000000000000000000000000000001 "
b00000000000000000000000000000000 #
b00000000000000000000000000000001 %
b00000000000000000000000000000000 &
#110000000
b00000000000000000000000000011111 "
b00000000000000000000000000011110 #
b00000000000000000000000000011111 %
b00000000000000000000000000011110 &
#120000000
b01010101010101010101010101010101 !
b00000000000000000000000000000000 "
b01010101010101010101010101010101 #
b01010101010101010101010101010101 $
b00000000000000000000000000000000 %
b01010101010101010101010101010101 &
#130000000
b11111111111111111111111111111111 "
b01010101010101010101010101010100 #
b11111111111111111111111111111111 %
b01010101010101010101010101010100 &
#140000000
b01010101010101010101010101010101 "
b10101010101010101010101010101010 #
b01010101010101010101010101010101 %
b10101010101010101010101010101010 &
#150000000
b10101010101010101010101010101010 "
b11111111111111111111111111111111 #
b10101010101010101010101010101010 %
b11111111111111111111111111111111 &
#160000000
b00000000000000000000000000000001 "
b01010101010101010101010101010110 #
b00000000000000000000000000000001 %
b01010101010101010101010101010110 &
#170000000
b00000000000000000000000000011111 "
b01010101010101010101010101110100 #
b00000000000000000000000000011111 %
b01010101010101010101010101110100 &
#180000000
b10101010101010101010101010101010 !
b00000000000000000000000000000000 "
b10101010101010101010101010101010 #
b10101010101010101010101010101010 $
b00000000000000000000000000000000 %
b10101010101010101010101010101010 &
#190000000
b11111111111111111111111111111111 "
b10101010101010101010101010101001 #
b11111111111111111111111111111111 %
b10101010101010101010101010101001 &
#200000000
b01010101010101010101010101010101 "
b11111111111111111111111111111111 #
b01010101010101010101010101010101 %
b11111111111111111111111111111111 &
#210000000
b10101010101010101010101010101010 "
b01010101010101010101010101010100 #
b10101010101010101010101010101010 %
b01010101010101010101010101010100 &
#220000000
b00000000000000000000000000000001 "
b10101010101010101010101010101011 #
b00000000000000000000000000000001 %
b10101010101010101010101010101011 &
#230000000
b00000000000000000000000000011111 "
b10101010101010101010101011001001 #
b00000000000000000000000000011111 %
b10101010101010101010101011001001 &
#240000000
b10000000000000000000000000000000 !
b00000000000000000000000000000000 "
b10000000000000000000000000000000 #
b10000000000000000000000000000000 $
b00000000000000000000000000000000 %
b10000000000000000000000000000000 &
#250000000
b11111111111111111111111111111111 "
b01111111111111111111111111111111 #
b11111111111111111111111111111111 %
b01111111111111111111111111111111 &
#260000000
b01010101010101010101010101010101 "
b11010101010101010101010101010101 #
b01010101010101010101010101010101 %
b11010101010101010101010101010101 &
#270000000
b10101010101010101010101010101010 "
b00101010101010101010101010101010 #
b10101010101010101010101010101010 %
b00101010101010101010101010101010 &
#280000000
b00000000000000000000000000000001 "
b10000000000000000000000000000001 #
b00000000000000000000000000000001 %
b10000000000000000000000000000001 &
#290000000
b00000000000000000000000000011111 "
b10000000000000000000000000011111 #
b00000000000000000000000000011111 %
b10000000000000000000000000011111 &
#300000000
b01111111111111111111111111111111 !
b00000000000000000000000000000000 "
b01111111111111111111111111111111 #
b01111111111111111111111111111111 $
b00000000000000000000000000000000 %
b01111111111111111111111111111111 &
#310000000
b11111111111111111111111111111111 "
b01111111111111111111111111111110 #
b11111111111111111111111111111111 %
b01111111111111111111111111111110 &
#320000000
b01010101010101010101010101010101 "
b11010101010101010101010101010100 #
b01010101010101010101010101010101 %
b11010101010101010101010101010100 &
#330000000
b10101010101010101010101010101010 "
b00101010101010101010101010101001 #
b10101010101010101010101010101010 %
b00101010101010101010101010101001 &
#340000000
b00000000000000000000000000000001 "
b10000000000000000000000000000000 #
b00000000000000000000000000000001 %
b10000000000000000000000000000000 &
#350000000
b00000000000000000000000000011111 "
b10000000000000000000000000011110 #
b00000000000000000000000000011111 %
b10000000000000000000000000011110 &
#360000000
b00100100011010001010110011110001 !
b01001000110100010101100111100010 "
b01101101001110100000011011010011 #
b00100100011010001010110011110001 $
b01001000110100010101100111100010 %
b01101101001110100000011011010011 &
#370000000
b10010001101000101011001111000101 !
b00100011010001010110011110001011 "
b10110100111010000001101101010000 #
b10010001101000101011001111000101 $
b00100011010001010110011110001011 %
b10110100111010000001101101010000 &
#380000000
b01000110100010101100111100010110 !
b10001101000101011001111000101101 "
b11010011101000000110110101000011 #
b01000110100010101100111100010110 $
b10001101000101011001111000101101 %
b11010011101000000110110101000011 &
#390000000
b00011010001010110011110001011010 !
b00110100010101100111100010110100 "
b01001110100000011011010100001110 #
b00011010001010110011110001011010 $
b00110100010101100111100010110100 %
b01001110100000011011010100001110 &
#400000000
b01101000101011001111000101101000 !
b11010001010110011110001011010001 "
b00111010000001101101010000111001 #
b01101000101011001111000101101000 $
b11010001010110011110001011010001 %
b00111010000001101101010000111001 &
#410000000
b10100010101100111100010110100010 !
b01000101011001111000101101000101 "
b11101000000110110101000011100111 #
b10100010101100111100010110100010 $
b01000101011001111000101101000101 %
b11101000000110110101000011100111 &
#420000000
b10001010110011110001011010001010 !
b00010101100111100010110100010100 "
b10100000011011010100001110011110 #
b10001010110011110001011010001010 $
b00010101100111100010110100010100 %
b10100000011011010100001110011110 &
#430000000
b00101011001111000101101000101000 !
b01010110011110001011010001010001 "
b10000001101101010000111001111001 #
b00101011001111000101101000101000 $
b01010110011110001011010001010001 %
b10000001101101010000111001111001 &
#440000000
b10101100111100010110100010100010 !
b01011001111000101101000101000101 "
b00000110110101000011100111100111 #
b10101100111100010110100010100010 $
b01011001111000101101000101000101 %
b00000110110101000011100111100111 &
#450000000
b10110011110001011010001010001010 !
b01100111100010110100010100010100 "
b00011011010100001110011110011110 #
b10110011110001011010001010001010 $
b01100111100010110100010100010100 %
b00011011010100001110011110011110 &
#460000000
b11001111000101101000101000101000 !
b10011110001011010001010001010001 "
b01101101010000111001111001111001 #
b11001111000101101000101000101000 $
b10011110001011010001010001010001 %
b01101101010000111001111001111001 &
#470000000
b00111100010110100010100010100011 !
b01111000101101000101000101000110 "
b10110101000011100111100111101001 #
b00111100010110100010100010100011 $
b01111000101101000101000101000110 %
b10110101000011100111100111101001 &
#480000000
b11110001011010001010001010001100 !
b11100010110100010100010100011000 "
b11010100001110011110011110100100 #
b11110001011010001010001010001100 $
b11100010110100010100010100011000 %
b11010100001110011110011110100100 &
#490000000
b11000101101000101000101000110001 !
b10001011010001010001010001100011 "
b01010000111001111001111010010100 #
b11000101101000101000101000110001 $
b10001011010001010001010001100011 %
b01010000111001111001111010010100 &
#500000000
b00010110100010100010100011000111 !
b00101101000101000101000110001110 "
b01000011100111100111101001010101 #
b00010110100010100010100011000111 $
b00101101000101000101000110001110 %
b01000011100111100111101001010101 &
#510000000
b01011010001010001010001100011101 !
b10110100010100010100011000111010 "
b00001110011110011110100101010111 #
b01011010001010001010001100011101 $
b10110100010100010100011000111010 %
b00001110011110011110100101010111 &
#520000000
b01101000101000101000110001110100 !
b11010001010001010001100011101001 "
b00111001111001111010010101011101 #
b01101000101000101000110001110100 $
b11010001010001010001100011101001 %
b00111001111001111010010101011101 &
#530000000
b10100010100010100011000111010010 !
b01000101000101000110001110100100 "
b11100111100111101001010101110110 #
b10100010100010100011000111010010 $
b01000101000101000110001110100100 %
b11100111100111101001010101110110 &
#540000000
b10001010001010001100011101001000 !
b00010100010100011000111010010000 "
b10011110011110100101010111011000 #
b10001010001010001100011101001000 $
b00010100010100011000111010010000 %
b10011110011110100101010111011000 &
#550000000
b00101000101000110001110100100000 !
b01010001010001100011101001000001 "
b01111001111010010101011101100001 #
b00101000101000110001110100100000 $
b01010001010001100011101001000001 %
b01111001111010010101011101100001 &
#560000000
b10100010100011000111010010000011 !
b01000101000110001110100100000111 "
b11100111101001010101110110001010 #
b10100010100011000111010010000011 $
b01000101000110001110100100000111 %
b11100111101001010101110110001010 &
#570000000
b10001010001100011101001000001110 !
b00010100011000111010010000011101 "
b10011110100101010111011000101011 #
b10001010001100011101001000001110 $
b00010100011000111010010000011101 %
b10011110100101010111011000101011 &
#580000000
b00101000110001110100100000111010 !
b01010001100011101001000001110101 "
b01111010010101011101100010101111 #
b00101000110001110100100000111010 $
b01010001100011101001000001110101 %
b01111010010101011101100010101111 &
#590000000
b10100011000111010010000011101011 !
b01000110001110100100000111010111 "
b11101001010101110110001011000010 #
b10100011000111010010000011101011 $
b01000110001110100100000111010111 %
b11101001010101110110001011000010 &
#600000000
b10001100011101001000001110101111 !
b00011000111010010000011101011110 "
b10100101010111011000101100001101 #
b10001100011101001000001110101111 $
b00011000111010010000011101011110 %
b10100101010111011000101100001101 &
#610000000
b00110001110100100000111010111100 !
b01100011101001000001110101111000 "
b10010101011101100010110000110100 #
b00110001110100100000111010111100 $
b01100011101001000001110101111000 %
b10010101011101100010110000110100 &
#620000000
b11000111010010000011101011110001 !
b10001110100100000111010111100010 "
b01010101110110001011000011010011 #
b11000111010010000011101011110001 $
b10001110100100000111010111100010 %
b01010101110110001011000011010011 &
#630000000
b00011101001000001110101111000100 !
b00111010010000011101011110001001 "
b01010111011000101100001101001101 #
b00011101001000001110101111000100 $
b00111010010000011101011110001001 %
b01010111011000101100001101001101 &
#640000000
b01110100100000111010111100010011 !
b11101001000001110101111000100110 "
b01011101100010110000110100111001 #
b01110100100000111010111100010011 $
b11101001000001110101111000100110 %
b01011101100010110000110100111001 &
#650000000
b11010010000011101011110001001100 !
b10100100000111010111100010011001 "
b01110110001011000011010011100101 #
b11010010000011101011110001001100 $
b10100100000111010111100010011001 %
b01110110001011000011010011100101 &
#660000000
b01001000001110101111000100110010 !
b10010000011101011110001001100100 "
b11011000101100001101001110010110 #
b01001000001110101111000100110010 $
b10010000011101011110001001100100 %
b11011000101100001101001110010110 &
#670000000
b00100000111010111100010011001000 !
b01000001110101111000100110010001 "
b01100010110000110100111001011001 #
b00100000111010111100010011001000 $
b01000001110101111000100110010001 %
b01100010110000110100111001011001 &
#680000000
b10000011101011110001001100100011 !
b00000111010111100010011001000110 "
b10001011000011010011100101101001 #
b10000011101011110001001100100011 $
b00000111010111100010011001000110 %
b10001011000011010011100101101001 &
#690000000
b00001110101111000100110010001101 !
b00011101011110001001100100011010 "
b00101100001101001110010110100111 #
b00001110101111000100110010001101 $
b00011101011110001001100100011010 %
b00101100001101001110010110100111 &
#700000000
b00111010111100010011001000110100 !
b01110101111000100110010001101001 "
b10110000110100111001011010011101 #
b00111010111100010011001000110100 $
b01110101111000100110010001101001 %
b10110000110100111001011010011101 &
#710000000
b11101011110001001100100011010010 !
b11010111100010011001000110100100 "
b11000011010011100101101001110110 #
b11101011110001001100100011010010 $
b11010111100010011001000110100100 %
b11000011010011100101101001110110 &
#720000000
b10101111000100110010001101001001 !
b01011110001001100100011010010010 "
b00001101001110010110100111011011 #
b10101111000100110010001101001001 $
b01011110001001100100011010010010 %
b00001101001110010110100111011011 &
#730000000
b10111100010011001000110100100100 !
b01111000100110010001101001001001 "
b00110100111001011010011101101101 #
b10111100010011001000110100100100 $
b01111000100110010001101001001001 %
b00110100111001011010011101101101 &
#740000000
b11110001001100100011010010010011 !
b11100010011001000110100100100110 "
b11010011100101101001110110111001 #
b11110001001100100011010010010011 $
b11100010011001000110100100100110 %
b11010011100101101001110110111001 &
#750000000
b11000100110010001101001001001101 !
b10001001100100011010010010011010 "
b01001110010110100111011011100111 #
b11000100110010001101001001001101 $
b10001001100100011010010010011010 %
b01001110010110100111011011100111 &
#760000000
b00010011001000110100100100110100 !
b00100110010001101001001001101001 "
b00111001011010011101101110011101 #
b00010011001000110100100100110100 $
b00100110010001101001001001101001 %
b00111001011010011101101110011101 &
#770000000
b01001100100011010010010011010011 !
b10011001000110100100100110100110 "
b11100101101001110110111001111001 #
b01001100100011010010010011010011 $
b10011001000110100100100110100110 %
b11100101101001110110111001111001 &
#780000000
b00110010001101001001001101001100 !
b01100100011010010010011010011001 "
b10010110100111011011100111100101 #
b00110010001101001001001101001100 $
b01100100011010010010011010011001 %
b10010110100111011011100111100101 &
#790000000
b11001000110100100100110100110010 !
b10010001101001001001101001100100 "
b01011010011101101110011110010110 #
b11001000110100100100110100110010 $
b10010001101001001001101001100100 %
b01011010011101101110011110010110 &
#800000000
b00100011010010010011010011001000 !
b01000110100100100110100110010000 "
b01101001110110111001111001011000 #
b00100011010010010011010011001000 $
b01000110100100100110100110010000 %
b01101001110110111001111001011000 &
#810000000
b10001101001001001101001100100000 !
b00011010010010011010011001000000 "
b10100111011011100111100101100000 #
b10001101001001001101001100100000 $
b00011010010010011010011001000000 %
b10100111011011100111100101100000 &
#820000000
b00110100100100110100110010000000 !
b01101001001001101001100100000000 "
b10011101101110011110010110000000 #
b00110100100100110100110010000000 $
b01101001001001101001100100000000 %
b10011101101110011110010110000000 &
#830000000
b11010010010011010011001000000001 !
b10100100100110100110010000000010 "
b01110110111001111001011000000011 #
b11010010010011010011001000000001 $
b10100100100110100110010000000010 %
b01110110111001111001011000000011 &
#840000000
b01001001001101001100100000000100 !
b10010010011010011001000000001001 "
b11011011100111100101100000001101 #
b01001001001101001100100000000100 $
b10010010011010011001000000001001 %
b11011011100111100101100000001101 &
#850000000
b00100100110100110010000000010011 !
b01001001101001100100000000100110 "
b01101110011110010110000000111001 #
b00100100110100110010000000010011 $
b01001001101001100100000000100110 %
b01101110011110010110000000111001 &
#860000000
b10010011010011001000000001001100 !
b00100110100110010000000010011001 "
b10111001111001011000000011100101 #
b10010011010011001000000001001100 $
b00100110100110010000000010011001 %
b10111001111001011000000011100101 &
#870000000
b01001101001100100000000100110011 !
b10011010011001000000001001100111 "
b11100111100101100000001110011010 #
b01001101001100100000000100110011 $
b10011010011001000000001001100111 %
b11100111100101100000001110011010 &
#880000000
b00110100110010000000010011001110 !
b01101001100100000000100110011101 "
b10011110010110000000111001101011 #
b00110100110010000000010011001110 $
b01101001100100000000100110011101 %
b10011110010110000000111001101011 &
#890000000
b11010011001000000001001100111011 !
b10100110010000000010011001110110 "
b01111001011000000011100110110001 #
b11010011001000000001001100111011 $
b10100110010000000010011001110110 %
b01111001011000000011100110110001 &
#900000000
b01001100100000000100110011101100 !
b10011001000000001001100111011000 "
b11100101100000001110011011000100 #
b01001100100000000100110011101100 $
b10011001000000001001100111011000 %
b11100101100000001110011011000100 &
#910000000
b00110010000000010011001110110001 !
b01100100000000100110011101100011 "
b10010110000000111001101100010100 #
b00110010000000010011001110110001 $
b01100100000000100110011101100011 %
b10010110000000111001101100010100 &
#920000000
b11001000000001001100111011000110 !
b10010000000010011001110110001100 "
b01011000000011100110110001010010 #
b11001000000001001100111011000110 $
b10010000000010011001110110001100 %
b01011000000011100110110001010010 &
#930000000
b00100000000100110011101100011001 !
b01000000001001100111011000110011 "
b01100000001110011011000101001100 #
b00100000000100110011101100011001 $
b01000000001001100111011000110011 %
b01100000001110011011000101001100 &
#940000000
b10000000010011001110110001100111 !
b00000000100110011101100011001111 "
b10000000111001101100010100110110 #
b10000000010011001110110001100111 $
b00000000100110011101100011001111 %
b10000000111001101100010100110110 &
#950000000
b00000001001100111011000110011110 !
b00000010011001110110001100111100 "
b00000011100110110001010011011010 #
b00000001001100111011000110011110 $
b00000010011001110110001100111100 %
b00000011100110110001010011011010 &
#960000000
b00000100110011101100011001111001 !
b00001001100111011000110011110011 "
b00001110011011000101001101101100 #
b00000100110011101100011001111001 $
b00001001100111011000110011110011 %
b00001110011011000101001101101100 &
#970000000
b00010011001110110001100111100110 !
b00100110011101100011001111001100 "
b00111001101100010100110110110010 #
b00010011001110110001100111100110 $
b00100110011101100011001111001100 %
b00111001101100010100110110110010 &
#980000000
b01001100111011000110011110011001 !
b10011001110110001100111100110010 "
b11100110110001010011011011001011 #
b01001100111011000110011110011001 $
b10011001110110001100111100110010 %
b11100110110001010011011011001011 &
#990000000
b00110011101100011001111001100100 !
b01100111011000110011110011001001 "
b10011011000101001101101100101101 #
b00110011101100011001111001100100 $
b01100111011000110011110011001001 %
b10011011000101001101101100101101 &
#1000000000
b11001110110001100111100110010010 !
b10011101100011001111001100100100 "
b01101100010100110110110010110110 #
b11001110110001100111100110010010 $
b10011101100011001111001100100100 %
b01101100010100110110110010110110 &
#1010000000
b00111011000110011110011001001001 !
b01110110001100111100110010010011 "
b10110001010011011011001011011100 #
b00111011000110011110011001001001 $
b01110110001100111100110010010011 %
b10110001010011011011001011011100 &
#1020000000
b11101100011001111001100100100111 !
b11011000110011110011001001001110 "
b11000101001101101100101101110101 #
b11101100011001111001100100100111 $
b11011000110011110011001001001110 %
b11000101001101101100101101110101 &
#1030000000
b10110001100111100110010010011100 !
b01100011001111001100100100111001 "
b00010100110110110010110111010101 #
b10110001100111100110010010011100 $
b01100011001111001100100100111001 %
b00010100110110110010110111010101 &
#1040000000
b11000110011110011001001001110010 !
b10001100111100110010010011100101 "
b01010011011011001011011101010111 #
b11000110011110011001001001110010 $
b10001100111100110010010011100101 %
b01010011011011001011011101010111 &
#1050000000
b00011001111001100100100111001011 !
b00110011110011001001001110010111 "
b01001101101100101101110101100010 #
b00011001111001100100100111001011 $
b00110011110011001001001110010111 %
b01001101101100101101110101100010 &
#1060000000
b01100111100110010010011100101110 !
b11001111001100100100111001011101 "
b00110110110010110111010110001011 #
b01100111100110010010011100101110 $
b11001111001100100100111001011101 %
b00110110110010110111010110001011 &
#1070000000
b10011110011001001001110010111011 !
b00111100110010010011100101110110 "
b11011011001011011101011000110001 #
b10011110011001001001110010111011 $
b00111100110010010011100101110110 %
b11011011001011011101011000110001 &
#1080000000
b01111001100100100111001011101101 !
b11110011001001001110010111011011 "
b01101100101101110101100011001000 #
b01111001100100100111001011101101 $
b11110011001001001110010111011011 %
b01101100101101110101100011001000 &
#1090000000
b11100110010010011100101110110110 !
b11001100100100111001011101101100 "
b10110010110111010110001100100010 #
b11100110010010011100101110110110 $
b11001100100100111001011101101100 %
b10110010110111010110001100100010 &
#1100000000
b10011001001001110010111011011001 !
b00110010010011100101110110110011 "
b11001011011101011000110010001100 #
b10011001001001110010111011011001 $
b00110010010011100101110110110011 %
b11001011011101011000110010001100 &
#1110000000
b01100100100111001011101101100110 !
b11001001001110010111011011001101 "
b00101101110101100011001000110011 #
b01100100100111001011101101100110 $
b11001001001110010111011011001101 %
b00101101110101100011001000110011 &
#1120000000
b10010010011100101110110110011011 !
b00100100111001011101101100110110 "
b10110111010110001100100011010001 #
b10010010011100101110110110011011 $
b00100100111001011101101100110110 %
b10110111010110001100100011010001 &
#1130000000
b01001001110010111011011001101100 !
b10010011100101110110110011011000 "
b11011101011000110010001101000100 #
b01001001110010111011011001101100 $
b10010011100101110110110011011000 %
b11011101011000110010001101000100 &
#1140000000
b00100111001011101101100110110001 !
b01001110010111011011001101100010 "
b01110101100011001000110100010011 #
b00100111001011101101100110110001 $
b01001110010111011011001101100010 %
b01110101100011001000110100010011 &
#1150000000
b10011100101110110110011011000101 !
b00111001011101101100110110001011 "
b11010110001100100011010001010000 #
b10011100101110110110011011000101 $
b00111001011101101100110110001011 %
b11010110001100100011010001010000 &
#1160000000
b01110010111011011001101100010111 !
b11100101110110110011011000101111 "
b01011000110010001101000101000110 #
b01110010111011011001101100010111 $
b11100101110110110011011000101111 %
b01011000110010001101000101000110 &
#1170000000
b11001011101101100110110001011111 !
b10010111011011001101100010111110 "
b01100011001000110100010100011101 #
b11001011101101100110110001011111 $
b10010111011011001101100010111110 %
b01100011001000110100010100011101 &
#1180000000
b00101110110110011011000101111101 !
b01011101101100110110001011111011 "
b10001100100011010001010001111000 #
b00101110110110011011000101111101 $
b01011101101100110110001011111011 %
b10001100100011010001010001111000 &
#1190000000
b10111011011001101100010111110111 !
b01110110110011011000101111101110 "
b00110010001101000101000111100101 #
b10111011011001101100010111110111 $
b01110110110011011000101111101110 %
b00110010001101000101000111100101 &
